{
    "data": [{
        "id": "8daff13e-bde3-4b40-a90b-6b34732da361",
        "type": "electronique",
        "description": "D'une grande simplicité et très ludique, vous l'utiliserez pour la couture de base, mais surtout pour tous les loisirs créatifs, sacs, trousses, personnalisation grâce aux lettrages, et aux points fantaisies ,customisation de vos vêtements, confection……. Ainsi qu’une multitude de réglage facilitant la couture !",
        "photo": [
            "https://i.pinimg.com/originals/24/16/0f/24160fd8fff1ce1716c44d0962c6867a.jpg",
            "https://i.pinimg.com/originals/70/3b/aa/703baae69605241553e9adc77f4281af.jpg",
            "https://i.pinimg.com/originals/75/a4/c2/75a4c2dde3d67995beca9e7d1526d94d.jpg"
        ]
    }]
}